{
  "metadata": {
    "csmSeq": 570,
    "domainId": "industrial-accident1",
    "ccfNo": 4,
    "cciNo": 2,
    "cnpClsNo": 3,
    "pageId": "4-2-3",
    "title": "근골격계질병의 업무상 질병 인정기준",
    "breadcrumb": [
      "책자형",
      "산업재해보상보험Ⅰ(업무상 재해)\n                \n                \n                    \n                    \n                        생활법령 내 검색\n                        \n                        \n                            \n                                생활법령 내 검색\n                                X\n                            \n                            \n                                \n                                \n                                \n                                \n                                    검색어\n                                    \n                                    검색\n                                \n                            \n                        \n                        \n                        \n                        \n                    \n                                            \n                    \n                    \n                    \n                        공유\n                        저장\n                        인쇄\n                        즐겨찾기"
    ],
    "sourceUrl": "https://www.easylaw.go.kr/CSP/CnpClsMain.laf?popMenu=ov&csmSeq=570&ccfNo=4&cciNo=2&cnpClsNo=3",
    "fetchedAt": "2026-03-07T14:59:16.136Z"
  },
  "content": {
    "textBlocks": [
      "근로자에게 일정한 원인으로 특정 신체부위에 부담을 주는 업무로 그 업무와 관련이 있는 근육, 인대, 힘줄, 추간판, 연골, 뼈 또는 이와 관련된 신경 및 혈관에 미세한 손상이 누적되어 통증이나 기능 저하가 초래되는 급성 또는 만성질환(근골격계 질병)이 발병된 경우에는 업무상 질병으로 봅니다.",
      "근골격계 질병의 의의 및 범위",
      "근골격계 질병의 의의",
      "“근골격계 질병”이란 특정 신체부위에 부담을 주는 업무로 그 업무와 관련이 있는 근육, 인대, 힘줄, 추간판, 연골, 뼈 또는 이와 관련된 신경 및 혈관에 미세한 손상이 누적되어 통증이나 기능 저하가 초래되는 급성 또는 만성질환을 말합니다[「뇌혈관 질병 또는 심장 질병 및 근골격계 질병의 업무상 질병 인정 여부 결정에 필요한 사항」(고용노동부 고시 제2022-40호, 2022.4. 28. 발령, 2022. 7. 1. 시행) 제2호가목1)].",
      "근골격계 질병의 범위",
      "근골격계 질병은 팔(上肢), 다리(下肢) 및 허리 부분으로 구분합니다[「뇌혈관 질병 또는 심장 질병 및 근골격계 질병의 업무상 질병 인정 여부 결정에 필요한 사항」 제2호가목2)].",
      "“팔 부분(上肢)”은 목, 어깨, 등, 위팔, 아래팔, 팔꿈치, 손목, 손 및 손가락의 부위를 말하며, 대표적 질병으로는 경추염좌, 경추간판탈출증, 회전근개건염, 팔꿈치의 내(외)상과염, 수부의 건염 및 건초염, 수근관증후군 등이 있습니다.",
      "“다리 부분(下肢)”은 둔부, 대퇴부, 무릎, 다리, 발목, 발 및 발가락의 부위를 말하며, 대표적 질병으로는 무릎의 반월상 연골손상, 슬개대퇴부 통증증후군, 발바닥의 근막염, 발과 발목의 건염 등이 있습니다.",
      "“허리 부분”은 요추 및 주변의 조직을 지칭하며 대표적 질병으로는 요부염좌, 요추간판탈출증 등이 있습니다.",
      "근골격계 질병의 업무상 질병 인정기준",
      "업무에 종사한 기간과 시간, 업무의 양과 강도, 업무수행 자세와 속도, 업무수행 장소의 구조 등이 근골격계에 부담을 주는 업무(이하 “신체부담업무”라 함)로서 다음의 어느 하나에 해당하는 업무에 종사한 경력이 있는 근로자의 팔·다리 또는 허리 부분의 근골격계 질병이 발생하거나 악화된 경우에는 업무상 질병으로 봅니다. 다만, 업무와 관련이 없는 다른 원인으로 발병한 경우에는 업무상 질병으로 보지 않습니다(「산업재해보상보험법」 제37조제5항 및 「산업재해보상보험법 시행령」 제34조제3항 및 별표 3 제2호가목).",
      "반복 동작이 많은 업무",
      "무리한 힘을 가해야 하는 업무",
      "부적절한 자세를 유지하는 업무",
      "진동 작업",
      "그 밖에 특정 신체 부위에 부담이 되는 상태에서 하는 업무",
      "신체부담업무로 인하여 기존 질병이 악화되었음이 의학적으로 인정되면 업무상 질병으로 봅니다(「산업재해보상보험법」 제37조제5항 및 「산업재해보상보험법 시행령」 제34조제3항 및 별표 3 제2호나목).",
      "신체부담업무로 인해 연령 증가에 따른 자연경과적 변화가 더욱 빠르게 진행된 것이 의학적으로 인정되면 업무상 질병으로 봅니다(「산업재해보상보험법」 제37조제5항 및 「산업재해보상보험법 시행령」 제34조제3항 및 별표 3 제2호다목).",
      "신체부담업무의 수행 과정에서 발생한 일시적인 급격한 힘의 작용으로 근골격계 질병이 발병하면 업무상 질병으로 봅니다(「산업재해보상보험법」 제37조제5항 및 「산업재해보상보험법 시행령」 제34조제3항 및 별표 3 제2호라목).",
      "신체부담업무를 수행한 작업력이 있는 근로자에게 업무수행 중 발생한 사고로 인해 나타나는 근골격계 질병은 업무상 질병의 판단 절차에 따릅니다[「뇌혈관 질병 또는 심장 질병 및 근골격계 질병의 업무상 질병 인정 여부 결정에 필요한 사항」 제2호다목1) 본문].",
      "※ 다만, 신체에 가해진 외력의 정도와 그에 따른 신체손상(골절, 인대손상, 연부조직 손상, 열상, 타박상 등)이 그 근로자의 직업력과 관계없이 사고로 발생한 것으로 의학적으로 인정되는 경우에는 업무상 사고의 판단 절차에 따릅니다[「뇌혈관 질병 또는 심장 질병 및 근골격계 질병의 업무상 질병 인정 여부 결정에 필요한 사항」 제2호다목1) 단서].",
      "√ 위의 “업무수행 중 발생한 사고”란 업무수행 중에 통상의 동작 또는 다른 동작에 의해 관절 부위에 급격한 힘이 돌발적으로 가해져 발생한 경우를 말합니다[「뇌혈관 질병 또는 심장 질병 및 근골격계 질병의 업무상 질병 인정 여부 결정에 필요한 사항」 제2호다목2) 전단].",
      "√ 이 경우 “급격한 힘이 돌발적으로 가해져 발생한 경우”를 판단할 때에는 신체부담업무에 따른 신체의 영향과 급격한 힘의 작용에 따른 신체의 영향을 종합적으로 고려하여 업무관련성 여부를 판단합니다[「뇌혈관 질병 또는 심장 질병 및 근골격계 질병의 업무상 질병 인정 여부 결정에 필요한 사항」 제2호다목2) 후단].",
      "업무관련성의 판단",
      "신체부담업무의 업무관련성을 판단할 때에는 신체부담정도, 직업력, 간헐적 작업 유무, 비고정작업 유무, 종사기간, 질병의 상태 등을 종합적으로 고려하여 판단합니다[「뇌혈관 질병 또는 심장 질병 및 근골격계 질병의 업무상 질병 인정 여부 결정에 필요한 사항」 제2호라목1)].",
      "위의 신체부담정도는 재해조사 내용을 토대로 인간공학전문가, 산업위생전문가, 산업의학 전문의 등 관련 전문가의 의견을 들어 평가하되, 필요한 경우 관련 전문가와 함께 재해조사를 하여 판단합니다[「뇌혈관 질병 또는 심장 질병 및 근골격계 질병의 업무상 질병 인정 여부 결정에 필요한 사항」 제2호라목2)]."
    ],
    "tables": []
  },
  "extracted": {
    "conditions": [
      "발병된 경우",
      "악화된 경우",
      "발병한 경우",
      "인정되는 경우",
      "발생한 경우",
      "필요한 경우",
      "발병된 경우에는",
      "악화된 경우에는",
      "발병한 경우에는",
      "인정되는 경우에는",
      "인정 여부",
      "업무관련성 여부"
    ],
    "lawRefs": [
      {
        "lawName": "산업재해보상보험법",
        "article": 37,
        "paragraph": 5,
        "fullText": "「산업재해보상보험법」 제37조제5항"
      },
      {
        "lawName": "산업재해보상보험법 시행령",
        "article": 34,
        "paragraph": 3,
        "fullText": "「산업재해보상보험법 시행령」 제34조제3항"
      },
      {
        "lawName": "산업재해보상보험법",
        "article": 37,
        "paragraph": 5,
        "fullText": "「산업재해보상보험법」 제37조제5항"
      },
      {
        "lawName": "산업재해보상보험법 시행령",
        "article": 34,
        "paragraph": 3,
        "fullText": "「산업재해보상보험법 시행령」 제34조제3항"
      },
      {
        "lawName": "산업재해보상보험법",
        "article": 37,
        "paragraph": 5,
        "fullText": "「산업재해보상보험법」 제37조제5항"
      },
      {
        "lawName": "산업재해보상보험법 시행령",
        "article": 34,
        "paragraph": 3,
        "fullText": "「산업재해보상보험법 시행령」 제34조제3항"
      },
      {
        "lawName": "산업재해보상보험법",
        "article": 37,
        "paragraph": 5,
        "fullText": "「산업재해보상보험법」 제37조제5항"
      },
      {
        "lawName": "산업재해보상보험법 시행령",
        "article": 34,
        "paragraph": 3,
        "fullText": "「산업재해보상보험법 시행령」 제34조제3항"
      }
    ],
    "amounts": [],
    "procedures": [
      "“근골격계 질병”이란 특정 신체부위에 부담을 주는 업무로 그 업무와 관련이 있는 근육, 인대, 힘줄, 추간판, 연골, 뼈 또는 이와 관련된 신경 및 혈관에 미세한 손상이 누적되어 통증이나 기능 저하가 초래되는 급성 또는 만성질환을 말합니다[「뇌혈관 질병 또는 심장 질병 및 근골격계 질병의 업무상 질병 인정 여부 결정에 필요한 사항」(고용노동부 고시 제2022-40호, 2022.4. 28. 발령, 2022. 7. 1. 시행) 제2호가목1)]."
    ]
  }
}